Metadata-Version: 2.1
Name: OSFResearchClient
Version: 0.2
Summary: Client Wrapper class for OSF API calls
Author: DisruptionLab
License: UNKNOWN
Platform: UNKNOWN
